lib2/__init__.py
lib2/preprocessing.py
lib2/version_util.py
lib2-1.0.0.dist-info/METADATA
lib2-1.0.0.dist-info/WHEEL
lib2-1.0.0.dist-info/RECORD
